ebes/__init__.py
ebes/trainer.py
ebes/types.py
ebes/data/__init__.py
ebes/data/accessors.py
ebes/data/batch_tfs.py
ebes/data/datasets.py
ebes/data/loading.py
ebes/data/utils.py
ebes/losses/__init__.py
ebes/losses/base.py
ebes/losses/contrastive.py
ebes/losses/multi_label.py
ebes/losses/neural_hawkes.py
ebes/metrics/__init__.py
ebes/metrics/custom.py
ebes/metrics/neural_hawkes.py
ebes/model/__init__.py
ebes/model/agg.py
ebes/model/basemodel.py
ebes/model/mtand.py
ebes/model/preprocess.py
ebes/model/seq2seq.py
ebes/model/utils.py
ebes/model/PrimeNet/__init__.py
ebes/model/PrimeNet/learn_time_emb.py
ebes/model/PrimeNet/models.py
ebes/model/PrimeNet/modules.py
ebes/model/convtran/AbsolutePositionalEncoding.py
ebes/model/convtran/Attention.py
ebes/model/convtran/model.py
ebes/model/convtran/utils.py
ebes/model/mamba/__init__.py
ebes/model/mamba/mamba_es.py
ebes/model/mlem/model.py
ebes/model/mlem/model_utils.py
ebes/model/ncde/ncde.py
ebes/model/neural_hawkes/clustering.py
ebes/model/neural_hawkes/ctlstm.py
ebes/model/neural_hawkes/seq_modelling.py
ebes/model/neural_hawkes/utils.py
ebes/pipeline/__init__.py
ebes/pipeline/base_runner.py
ebes/pipeline/utils.py
ebes/pipeline/runners/__init__.py
ebes/pipeline/runners/evaluate.py
ebes/pipeline/runners/primenet.py
ebes/pipeline/runners/supervised.py
ebes/pipeline/runners/unsupervised.py
ebes/utils/__init__.py
ebes/utils/general.py
ebes/utils/reproduce.py
ebes-0.0.8.dist-info/licenses/LICENSE.md
ebes-0.0.8.dist-info/METADATA
ebes-0.0.8.dist-info/WHEEL
ebes-0.0.8.dist-info/top_level.txt
ebes-0.0.8.dist-info/RECORD
